bot_tools/__init__.py
bot_tools-2.0.2.dist-info/LICENSE
bot_tools-2.0.2.dist-info/METADATA
bot_tools-2.0.2.dist-info/WHEEL
bot_tools-2.0.2.dist-info/top_level.txt
bot_tools-2.0.2.dist-info/RECORD
