Metadata-Version: 2.1
Name: bot-tools
Version: 2.0.2
Summary: Common tools for python bots
Home-page: https://github.com/onlythor/bot_tools
Author: Thor
Author-email: theonlythor@protonmail.com
License: UNKNOWN
Platform: UNKNOWN
Classifier: Programming Language :: Python :: 3
Classifier: Programming Language :: Python :: 3.6
Classifier: Programming Language :: Python :: 3.7
Requires-Python: >=3.6
Requires-Dist: colorama
